Exceptions/__init__.py
Exceptions/cannot_connect_to_ncat_exception.py
Exceptions/ncat_timeout_exception.py
Exceptions/required_parameter_missing_exception.py
ncatapi/__init__.py
ncatapi/ncat.py
ncat_api-0.0.2.dist-info/METADATA
ncat_api-0.0.2.dist-info/WHEEL
ncat_api-0.0.2.dist-info/licenses/LICENSE.txt
ncat_api-0.0.2.dist-info/RECORD
