Metadata-Version: 2.1
Name: ncat-api
Version: 0.0.2
Summary: NCAT API Endpoint wrapper for python.
Project-URL: Homepage, https://github.com/National-Flood-Experts/ncat-python
Project-URL: Bug Tracker, https://github.com/National-Flood-Experts/ncat-python/issues
Author-email: Alexander Faus <alexfaus08@gmail.com>
License-File: LICENSE.txt
Classifier: License :: OSI Approved :: MIT License
Classifier: Operating System :: OS Independent
Classifier: Programming Language :: Python :: 3
Requires-Python: >=3.7
Requires-Dist: requests
